reactome_anywidget/__init__.py
reactome_anywidget/_widget.py
reactome_anywidget/static/widget.js
reactome_anywidget-0.0.0a0.dist-info/METADATA
reactome_anywidget-0.0.0a0.dist-info/WHEEL
reactome_anywidget-0.0.0a0.dist-info/RECORD
